lino_welfare/__init__.py
lino_welfare/migrate.py
lino_welfare/migrate_old.py
lino_welfare/modlib/__init__.py
lino_welfare/modlib/active_job_search__init__.py
lino_welfare/modlib/accounting/__init__.py
lino_welfare/modlib/accounting/models.py
lino_welfare/modlib/accounting/fixtures/__init__.py
lino_welfare/modlib/accounting/fixtures/demo.py
lino_welfare/modlib/accounting/fixtures/std.py
lino_welfare/modlib/accounting/fixtures/std_journals.py
lino_welfare/modlib/active_job_search/__init__.py
lino_welfare/modlib/active_job_search/models.py
lino_welfare/modlib/active_job_search/fixtures/__init__.py
lino_welfare/modlib/active_job_search/fixtures/demo.py
lino_welfare/modlib/aids/__init__.py
lino_welfare/modlib/aids/choicelists.py
lino_welfare/modlib/aids/mixins.py
lino_welfare/modlib/aids/models.py
lino_welfare/modlib/aids/roles.py
lino_welfare/modlib/aids/config/aids/Confirmation/certificate.body.html
lino_welfare/modlib/aids/config/aids/Confirmation/clothing_bank.body.html
lino_welfare/modlib/aids/config/aids/Confirmation/default.body.html
lino_welfare/modlib/aids/config/aids/Confirmation/fixed_income.body.html
lino_welfare/modlib/aids/config/aids/Confirmation/food_bank.body.html
lino_welfare/modlib/aids/config/aids/Confirmation/foreigner_income.body.html
lino_welfare/modlib/aids/config/aids/Confirmation/furniture.body.html
lino_welfare/modlib/aids/config/aids/Confirmation/heating_refund.body.html
lino_welfare/modlib/aids/config/aids/Confirmation/integ_income.body.html
lino_welfare/modlib/aids/config/aids/Confirmation/medical_refund.body.html
lino_welfare/modlib/aids/config/aids/Confirmation/urgent_medical_care.body.html
lino_welfare/modlib/aids/fixtures/__init__.py
lino_welfare/modlib/aids/fixtures/demo.py
lino_welfare/modlib/aids/fixtures/std.py
lino_welfare/modlib/art60/__init__.py
lino_welfare/modlib/art60/models.py
lino_welfare/modlib/art60/config/art60/Contract/Default.odt
lino_welfare/modlib/art60/fixtures/__init__.py
lino_welfare/modlib/art60/fixtures/std.py
lino_welfare-25.11.0.dist-info/METADATA
lino_welfare-25.11.0.dist-info/WHEEL
lino_welfare-25.11.0.dist-info/licenses/AUTHORS.rst
lino_welfare-25.11.0.dist-info/licenses/AUTHORS.rst~
lino_welfare-25.11.0.dist-info/licenses/COPYING
lino_welfare-25.11.0.dist-info/licenses/COPYING~
lino_welfare-25.11.0.dist-info/RECORD
